GP8XXX_IIC/__init__.py
GP8XXX_IIC-0.0.4.dist-info/LICENSE
GP8XXX_IIC-0.0.4.dist-info/METADATA
GP8XXX_IIC-0.0.4.dist-info/WHEEL
GP8XXX_IIC-0.0.4.dist-info/top_level.txt
GP8XXX_IIC-0.0.4.dist-info/RECORD
