Metadata-Version: 2.1
Name: GP8XXX-IIC
Version: 0.0.4
Summary: The GP8XXX Python module offers an intuitive interface for controlling DAC (Digital to Analog Converter) devices via the I2C protocol. With support for various DAC models.
Home-page: https://github.com/joe2824/GP8XXX_IIC/
Author: Joel Klein
License: UNKNOWN
Project-URL: Bug Tracker, https://github.com/joe2824/GP8XXX_IIC/issues
Project-URL: Github, https://github.com/joe2824/GP8XXX_IIC/
Keywords: Raspberry Pi,Raspi,GP8403,GP8503,GP8211S,GP8512,GP8413,GP8302,DAC
Platform: UNKNOWN
Classifier: Development Status :: 4 - Beta
Classifier: Programming Language :: Python :: 3
Classifier: License :: OSI Approved :: MIT License
Classifier: Operating System :: POSIX :: Linux
Requires-Python: >=3
Requires-Dist: smbus2
